{"_comment":"after email below, I have removed phone, changed <label> to <title>","basics":{"name":"Arnav Gautam","title":"Student","image":"","email":"arnavg@iitbhilai.ac.in","url":"arnavwinner.github.io","summary":"Undergraduate in Computer Science and Engineering","location":{"address":"Kanhar, Durg, IIT Bhilai","postalCode":"491002","city":"Durg","countryCode":"IND","region":"Bhilai"},"profiles":[{"network":"Twitter","username":"ArnavGautam24","url":"https://twitter.com/ArnavGautam24"},{"network":"Github","username":"arnavwinner","url":"https://github.com/arnavwinner"}]},"work":[{"name":"Visa Inc.","position":"Software Engineer Intern","url":"https://www.visa.co.in/","startDate":"2024-05-07","endDate":"2024-07-13","summary":"Developed APIs for intra-visa network","highlights":["Worked at Data and AI Platform","with Microservices and API Team"]}],"volunteer":[{"organization":"EBSB","location":"Bhilai, India","position":"Core Member","url":"https://ekbharat.gov.in/pages/ActivityDetails?ID=jSE8s0TsEvFygIQiMaSnhA==","startDate":"2022-04-01","endDate":"2023-04-01","summary":"Worked as Content Head at EBSB (Ek Bharat Shrestha Bharat)","highlights":["Taught in our local Sejbahar Government School","Promoted Patriotism towards the nation by unifying different cultures of India"]},{"organization":"Ingenuity","location":"Bhilai, India","position":"Core Member","startDate":"2022-04-01","endDate":"2023-04-01","summary":"A Competitive Programming Club of IIT Bhilai: Handled Club Activities and supported algorithmic problem solving","highlights":["Hands on Data Structure and Algorithms, participated in workshops","Got in Top 5 in Lockout Tournament (Intra-college event)"]},{"organization":"Ingenuity","location":"Bhilai, India","position":"Coordinator","startDate":"2023-04-01","endDate":"2024-04-01","summary":"A Competitive Programming Club of IIT Bhilai: Coordinated Club Activities","highlights":["Workshops taken every month each one teaching a specific algorithmic concept",""]}],"education":[{"institution":"Indian Institute of Technology, Bhilai","location":"Bhilai, India","url":"https://www.iitbhilai.ac.in/","area":"Computer Science and Engineering","studyType":"Bachelors","startDate":"2021-11-29","endDate":"Present","score":"7.91 (scale out of 10)"},{"institution":"DLF Public School","location":"Ghaziabad, India","url":"https://www.dlps.co.in/","area":"Student","studyType":"Till Middle School","startDate":"2006-04-01","endDate":"2017-03-31","score":"9.1 (scale out of 10)"},{"institution":"Sri Venkateshwar International School","location":"Dwarka, New Delhi","url":"https://www.svis.org.in/","area":"Student","studyType":"High School","startDate":"2017-04-01","endDate":"2019-03-31","score":"95.6%"},{"institution":"OPG World School","location":"Dwarka, New Delhi","url":"https://www.svis.org.in/","area":"Student","studyType":"High School","startDate":"2019-04-01","endDate":"2021-03-31","score":"91.4%"}],"skills":[{"name":"Programming Languages","level":"Intermediate","icon":"fa-solid fa-hashtag","keywords":["C++","Python","Java"]}],"languages":[{"language":"Hindi","fluency":"Native speaker","icon":""},{"language":"English","fluency":"Fluent","icon":""},{"language":"French","fluency":"Elementary Level","icon":""}],"interests":[{"name":"Algorithmic Problem Solving","icon":"fa-solid fa-tag","keywords":["Data Structures","Graph Theory","Dynamic Programming"]}]}